funcyou/__init__.py
funcyou/convert.py
funcyou/dataset.py
funcyou/hello.py
funcyou/plot.py
funcyou/utils.py
funcyou/preprocessing/__init__.py
funcyou/preprocessing/image.py
funcyou/preprocessing/text.py
funcyou/pytorch/__init__.py
funcyou/pytorch/image.py
funcyou/pytorch/utils.py
funcyou/sklearn/__init__.py
funcyou/sklearn/clusters.py
funcyou/sklearn/grid_search_utils.py
funcyou/sklearn/metrics.py
funcyou/tensorflow/__init__.py
funcyou/tensorflow/callbacks.py
funcyou/tensorflow/utils.py
funcyou/timeseries/__init__.py
funcyou/timeseries/utils.py
funcyou-1.1.2.dist-info/METADATA
funcyou-1.1.2.dist-info/WHEEL
funcyou-1.1.2.dist-info/top_level.txt
funcyou-1.1.2.dist-info/RECORD
