Metadata-Version: 2.1
Name: funcyou
Version: 1.1.2
Summary: useful functions to reuse and save time
Author: Tikendra sahu
Author-email: tikendraksahu1029@gmail.com
Requires-Dist: matplotlib
Requires-Dist: scikit-learn
Requires-Dist: pandas
Requires-Dist: numpy
Requires-Dist: kaggle
Requires-Dist: seaborn
